dataknobs_config/__init__.py
dataknobs_config/binding_resolver.py
dataknobs_config/builders.py
dataknobs_config/config.py
dataknobs_config/environment.py
dataknobs_config/environment_aware.py
dataknobs_config/environment_config.py
dataknobs_config/exceptions.py
dataknobs_config/inheritance.py
dataknobs_config/py.typed
dataknobs_config/references.py
dataknobs_config/settings.py
dataknobs_config/substitution.py
dataknobs_config/examples/__init__.py
dataknobs_config/examples/cache.py
dataknobs_config/examples/database.py
dataknobs_config/examples/services.py
dataknobs_config-0.3.3.dist-info/METADATA
dataknobs_config-0.3.3.dist-info/WHEEL
dataknobs_config-0.3.3.dist-info/RECORD
