Metadata-Version: 2.4
Name: dataknobs-config
Version: 0.3.3
Summary: Modular configuration system with composable settings and environment variable overrides
Author-email: KBS Labs <info@kbs-labs.com>
License: MIT
Classifier: Development Status :: 3 - Alpha
Classifier: Intended Audience :: Developers
Classifier: License :: OSI Approved :: MIT License
Classifier: Programming Language :: Python :: 3
Classifier: Programming Language :: Python :: 3.10
Classifier: Programming Language :: Python :: 3.11
Classifier: Programming Language :: Python :: 3.12
Requires-Python: >=3.10
Requires-Dist: dataknobs-common>=1.0.1
Requires-Dist: pyyaml>=6.0
Provides-Extra: dev
Requires-Dist: black>=22.0; extra == 'dev'
Requires-Dist: flake8>=5.0; extra == 'dev'
Requires-Dist: mypy>=1.0; extra == 'dev'
Requires-Dist: pytest-cov>=4.0; extra == 'dev'
Requires-Dist: pytest>=7.0; extra == 'dev'
Requires-Dist: types-pyyaml>=6.0; extra == 'dev'
